{
  "person": {
    "name": {
      "fullName": "Angela Knight",
      "lastName": "Knight",
      "firstName": "Angela"
    },
    "gender": "female",
    "birthYear": 1956,
    "birthDayAndMonth": "09-23"
  },
  "loyalty": {
    "points": 686162,
    "joinDate": "2022-03-30",
    "loyaltyID": 2201324126990
  },
  "consents": {
    "collect": {
      "val": "n"
    },
    "marketing": {
      "preferred": "email"
    }
  },
  "createDate": "2024-11-29T14:38:24.310071",
  "homeAddress": {
    "city": "New Jeffrey",
    "country": "United States",
    "street1": "88979 Jordan Knoll",
    "postalCode": "79264",
    "countryCode": "US"
  },
  "mobilePhone": {
    "number": "(451)260-6463x374"
  },
  "testProfile": "true",
  "userAccount": {
    "ID": "324126990"
  },
  "personalEmail": {
    "address": "angelaknight@example.com"
  },
  "identification": {
    "email": "angelaknight@example.com",
    "loyaltyId": 2201324126990,
    "customerId": "324126990",
    "phoneNumber": "(451)260-6463x374"
  },
  "individualCharacteristics": {
    "core": {
      "age": 68,
      "favouriteCategory": "Mens",
      "favouriteSubCategory": "Pants"
    },
    "retail": {
      "shoeSize": 35,
      "pantsSize": "XL",
      "shirtSize": "XXL",
      "favoriteColor": "Blue"
    }
  }
}